LICENSE.md
MANIFEST.in
README.md
pyproject.toml
src/himatcal/.himatcal.yaml
src/himatcal/__init__.py
src/himatcal/py.typed
src/himatcal/settings.py
src/himatcal.egg-info/PKG-INFO
src/himatcal.egg-info/SOURCES.txt
src/himatcal.egg-info/dependency_links.txt
src/himatcal.egg-info/entry_points.txt
src/himatcal.egg-info/requires.txt
src/himatcal.egg-info/top_level.txt
src/himatcal/_cli/cli.py
src/himatcal/atoms/__init__.py
src/himatcal/atoms/core.py
src/himatcal/atoms/parser.py
src/himatcal/calculator/__init__.py
src/himatcal/calculator/aio_ani.py
src/himatcal/calculator/gaussian_mcd.py
src/himatcal/calculator/mlp.py
src/himatcal/calculator/orca_mcd.py
src/himatcal/calculator/pyscf_calculator.py
src/himatcal/calculator/aimnet/.gitignore
src/himatcal/calculator/aimnet/__init__.py
src/himatcal/calculator/aimnet/aimnet2ase.py
src/himatcal/calculator/aimnet/aimnet2pysis.py
src/himatcal/calculator/aimnet/core.py
src/himatcal/calculator/aimnet/ensemble.py
src/himatcal/calculator/aimnet/models.py
src/himatcal/calculator/aimnet/nblist.py
src/himatcal/calculator/xtb/__init__.py
src/himatcal/calculator/xtb/_io.py
src/himatcal/calculator/xtb/calculator.py
src/himatcal/recipes/__init__.py
src/himatcal/recipes/crest/__init__.py
src/himatcal/recipes/crest/_base.py
src/himatcal/recipes/crest/core.py
src/himatcal/recipes/electrolyte/__init__.py
src/himatcal/recipes/electrolyte/core.py
src/himatcal/recipes/electrolyte/redox.py
src/himatcal/recipes/electrolyte/sol_stru/__init__.py
src/himatcal/recipes/electrolyte/sol_stru/_base.py
src/himatcal/recipes/electrolyte/sol_stru/build_box.py
src/himatcal/recipes/electrolyte/sol_stru/core.py
src/himatcal/recipes/electrolyte/sol_stru/genFF.py
src/himatcal/recipes/electrolyte/sol_stru/md.py
src/himatcal/recipes/gaussian/__init__.py
src/himatcal/recipes/gaussian/_base.py
src/himatcal/recipes/gaussian/core.py
src/himatcal/recipes/gaussian/flow.py
src/himatcal/recipes/gsm/DE_GSM.py
src/himatcal/recipes/gsm/SE_GSM.py
src/himatcal/recipes/gsm/__init__.py
src/himatcal/recipes/gsm/core.py
src/himatcal/recipes/materials/__init__.py
src/himatcal/recipes/materials/core.py
src/himatcal/recipes/materials/diffubarrier.py
src/himatcal/recipes/mcd/__init__.py
