Metadata-Version: 2.4
Name: himatcal
Version: 0.1.9
Summary: High throughput material calculation
Author-email: Congcong Sun <suncongcong000@foxmail.com>
License: BSD-3-Clause
Project-URL: repository, https://github.com/CCSun21/himatcal
Project-URL: documentation, https://CCSun21.github.io/himatcal/
Project-URL: changelog, https://github.com/CCSun21/himatcal/blob/main/CHANGELOG.md
Classifier: Development Status :: 3 - Alpha
Classifier: Intended Audience :: Science/Research
Classifier: Programming Language :: Python :: 3
Classifier: Programming Language :: Python :: 3.10
Classifier: Programming Language :: Python :: 3.11
Classifier: Programming Language :: Python :: 3.12
Classifier: Programming Language :: Python :: 3.13
Classifier: Intended Audience :: Science/Research
Classifier: Topic :: Scientific/Engineering
Classifier: Operating System :: Microsoft :: Windows
Classifier: Operating System :: Unix
Classifier: Operating System :: MacOS
Requires-Python: <3.13,>=3.10
License-File: LICENSE.md
Requires-Dist: pandas>=2.2.3
Requires-Dist: quacc>=0.12.1
Provides-Extra: molecule
Requires-Dist: chemspipy>=2.0.0; extra == "molecule"
Requires-Dist: goodvibes>=3.2; extra == "molecule"
Requires-Dist: ipython>=8.32.0; extra == "molecule"
Requires-Dist: rdkit>=2024.9.5; extra == "molecule"
Provides-Extra: dev
Requires-Dist: pytest-cov>=6.0.0; extra == "dev"
Requires-Dist: ruff>=0.9.6; extra == "dev"
Provides-Extra: md
Requires-Dist: boltons>=25.0.0; extra == "md"
Requires-Dist: ele>=0.2.0; extra == "md"
Requires-Dist: foyer; extra == "md"
Requires-Dist: gmso; extra == "md"
Requires-Dist: importlib-resources>=6.5.2; extra == "md"
Requires-Dist: lark>=1.2.2; extra == "md"
Requires-Dist: lxml>=5.3.1; extra == "md"
Requires-Dist: mbuild; extra == "md"
Requires-Dist: mdtraj>=1.10.3; extra == "md"
Requires-Dist: openmm>=8.2.0; extra == "md"
Requires-Dist: parmed>=4.3.0; extra == "md"
Requires-Dist: symengine>=0.14.0; extra == "md"
Requires-Dist: treelib>=1.7.1; extra == "md"
Requires-Dist: unyt>=3.0.4; extra == "md"
Provides-Extra: mlp
Requires-Dist: mace>=1.1.2; extra == "mlp"
Dynamic: license-file
